pytest_chdir/__init__.py
pytest_chdir/plugin.py
pytest_chdir-0.1.3.dist-info/entry_points.txt
pytest_chdir-0.1.3.dist-info/LICENSE
pytest_chdir-0.1.3.dist-info/WHEEL
pytest_chdir-0.1.3.dist-info/METADATA
pytest_chdir-0.1.3.dist-info/RECORD
