Metadata-Version: 2.1
Name: pytest-chdir
Version: 0.1.3
Summary: A pytest fixture for changing current working directory
License: MIT
Author: Masahiro Wada
Author-email: argon.argon.argon@gmail.com
Requires-Python: >=3.6,<4.0
Classifier: License :: OSI Approved :: MIT License
Classifier: Programming Language :: Python :: 3
Classifier: Programming Language :: Python :: 3.6
Classifier: Programming Language :: Python :: 3.7
Classifier: Programming Language :: Python :: 3.8
Requires-Dist: pytest (>=5.0.0,<6.0.0)
